odoo/addons/sale_blanket_order_readonly_states_extended/LICENSE
odoo/addons/sale_blanket_order_readonly_states_extended/README.rst
odoo/addons/sale_blanket_order_readonly_states_extended/__init__.py
odoo/addons/sale_blanket_order_readonly_states_extended/__manifest__.py
odoo/addons/sale_blanket_order_readonly_states_extended/images/screen.png
odoo/addons/sale_blanket_order_readonly_states_extended/models/__init__.py
odoo/addons/sale_blanket_order_readonly_states_extended/models/blanket_order.py
odoo/addons/sale_blanket_order_readonly_states_extended/static/description/icon.png
odoo/addons/sale_blanket_order_readonly_states_extended/static/description/index.html
odoo/addons/sale_blanket_order_readonly_states_extended/tests/TEST_INSTRUCTIONS.rst
odoo/addons/sale_blanket_order_readonly_states_extended/views/view_blanket_order_form.xml
odoo_addon_sale_blanket_order_readonly_states_extended-16.0.1.0.0.dist-info/METADATA
odoo_addon_sale_blanket_order_readonly_states_extended-16.0.1.0.0.dist-info/WHEEL
odoo_addon_sale_blanket_order_readonly_states_extended-16.0.1.0.0.dist-info/top_level.txt
odoo_addon_sale_blanket_order_readonly_states_extended-16.0.1.0.0.dist-info/RECORD
