Metadata-Version: 2.1
Name: odoo-addon-sale_blanket_order_readonly_states_extended
Version: 16.0.1.0.0
Requires-Python: >=3.10
Requires-Dist: odoo-addon-sale_blanket_order_contact_person>=16.0dev,<16.1dev
Requires-Dist: odoo-addon-sale_blanket_order_invoice_shipping_partner>=16.0dev,<16.1dev
Requires-Dist: odoo-addon-sale_blanket_order_readonly_states>=16.0dev,<16.1dev
Requires-Dist: odoo-addon-sale_blanket_order_stock_terms>=16.0dev,<16.1dev
Requires-Dist: odoo>=16.0a,<16.1dev
Summary: Sets readonly states for other sale blanket order modules.
Home-page: https://www.mint-system.ch/
License: AGPL-3
Author: Mint System GmbH
Classifier: Programming Language :: Python
Classifier: Framework :: Odoo
Classifier: Framework :: Odoo :: 16.0
Classifier: License :: OSI Approved :: GNU Affero General Public License v3
